cellular_modem/__init__.py
cellular_modem-0.0.1.dist-info/LICENSE
cellular_modem-0.0.1.dist-info/METADATA
cellular_modem-0.0.1.dist-info/WHEEL
cellular_modem-0.0.1.dist-info/top_level.txt
cellular_modem-0.0.1.dist-info/RECORD
